cognito_user_shell/__init__.py
cognito_user_shell/client.py
cognito_user_shell/shell.py
cognito_user_shell/utils.py
cognito_user_shell-0.1.8.dist-info/LICENSE
cognito_user_shell-0.1.8.dist-info/METADATA
cognito_user_shell-0.1.8.dist-info/WHEEL
cognito_user_shell-0.1.8.dist-info/top_level.txt
cognito_user_shell-0.1.8.dist-info/RECORD
