Metadata-Version: 2.1
Name: cognito-user-shell
Version: 0.1.8
Summary: Extendable shell/CLI tool with AWS Cognito authentication.
Home-page: https://github.com/jussiniinikoski/cognito-user-shell
Author: Jussi Niinikoski
Author-email: jussi.niinikoski@perjantai.fi
Classifier: Programming Language :: Python :: 3
Classifier: License :: OSI Approved :: MIT License
Classifier: Operating System :: OS Independent
Requires-Python: >=3.6
License-File: LICENSE
Requires-Dist: boto3
Requires-Dist: requests
